html_to_markdown-2.24.4.dist-info/RECORD
html_to_markdown-2.24.4.dist-info/WHEEL
html_to_markdown-2.24.4.dist-info/METADATA
html_to_markdown-2.24.4.dist-info/licenses/LICENSE
html_to_markdown-2.24.4.data/scripts/html-to-markdown
html_to_markdown/options.py
html_to_markdown/_html_to_markdown.pyi
html_to_markdown/_html_to_markdown.abi3.so
html_to_markdown/__init__.py
html_to_markdown/api.py
html_to_markdown/v1_compat.py
html_to_markdown/cli.py
html_to_markdown/py.typed
html_to_markdown/exceptions.py
html_to_markdown/cli_proxy.py
html_to_markdown/__main__.py
html_to_markdown/bin/html-to-markdown
