Metadata-Version: 2.4
Name: html-to-markdown
Version: 2.24.4
Classifier: Development Status :: 5 - Production/Stable
Classifier: Environment :: Console
Classifier: Intended Audience :: Developers
Classifier: License :: OSI Approved :: MIT License
Classifier: Operating System :: OS Independent
Classifier: Programming Language :: Python :: 3 :: Only
Classifier: Programming Language :: Python :: 3.10
Classifier: Programming Language :: Python :: 3.11
Classifier: Programming Language :: Python :: 3.12
Classifier: Programming Language :: Python :: 3.13
Classifier: Programming Language :: Python :: 3.14
Classifier: Programming Language :: Rust
Classifier: Topic :: Software Development :: Libraries :: Python Modules
Classifier: Topic :: Text Processing
Classifier: Topic :: Text Processing :: Markup
Classifier: Topic :: Text Processing :: Markup :: HTML
Classifier: Topic :: Text Processing :: Markup :: Markdown
Classifier: Typing :: Typed
License-File: LICENSE
Summary: High-performance HTML to Markdown converter powered by Rust with a clean Python API
Keywords: cli-tool,converter,html,html2markdown,html5,markdown,markup,parser,rust,text-processing
Home-Page: https://github.com/kreuzberg-dev/html-to-markdown
Author-email: Na'aman Hirschfeld <nhirschfeld@gmail.com>
Requires-Python: >=3.10
Project-URL: Changelog, https://github.com/kreuzberg-dev/html-to-markdown/releases
Project-URL: Homepage, https://github.com/kreuzberg-dev/html-to-markdown
Project-URL: Issues, https://github.com/kreuzberg-dev/html-to-markdown/issues
Project-URL: Repository, https://github.com/kreuzberg-dev/html-to-markdown.git
